.travis.yml
LICENSE.md
MANIFEST.in
Makefile
README.md
pylama.ini
pytest.ini
setup.cfg
setup.py
test_requirements.txt
tox.ini
datapackage_pipelines_sourcespec_registry/VERSION
datapackage_pipelines_sourcespec_registry/__init__.py
datapackage_pipelines_sourcespec_registry/generator.py
datapackage_pipelines_sourcespec_registry.egg-info/PKG-INFO
datapackage_pipelines_sourcespec_registry.egg-info/SOURCES.txt
datapackage_pipelines_sourcespec_registry.egg-info/dependency_links.txt
datapackage_pipelines_sourcespec_registry.egg-info/not-zip-safe
datapackage_pipelines_sourcespec_registry.egg-info/requires.txt
datapackage_pipelines_sourcespec_registry.egg-info/top_level.txt
datapackage_pipelines_sourcespec_registry/processors/__init__.py
datapackage_pipelines_sourcespec_registry/registry/__init__.py
datapackage_pipelines_sourcespec_registry/registry/registry.py
datapackage_pipelines_sourcespec_registry/schemas/sourcespec_registry_schema.json